watchpdf/__init__.py
watchpdf/main.py
watchpdf/utils.py
watchpdf-0.0.1.data/scripts/watchpdf
watchpdf-0.0.1.dist-info/LICENSE
watchpdf-0.0.1.dist-info/METADATA
watchpdf-0.0.1.dist-info/WHEEL
watchpdf-0.0.1.dist-info/top_level.txt
watchpdf-0.0.1.dist-info/RECORD
