Metadata-Version: 2.1
Name: watchpdf
Version: 0.0.1
Summary: Watch and rename accedmic papers
Home-page: https://github.com/defaultobject/watchpdf
Author: O Hamelijnck
Author-email: ohamelijnck@turing.ac.uk
Classifier: Programming Language :: Python :: 3
Classifier: License :: OSI Approved :: MIT License
Classifier: Operating System :: OS Independent
Requires-Python: >=3.6
License-File: LICENSE
Requires-Dist: typer
Requires-Dist: watchdog
Requires-Dist: pdf-renamer (==1.0rc9)
